pionex_py/__init__.py
pionex_py/__version__.py
pionex_py/internal/__init__.py
pionex_py/internal/generate_signature.py
pionex_py/internal/PionexExceptions.py
pionex_py/internal/RestClient.py
pionex_py/internal/WebsocketClient.py
pionex_py/restful/__init__.py
pionex_py/restful/Account.py
pionex_py/restful/Common.py
pionex_py/restful/Markets.py
pionex_py/restful/Orders.py
pionex_py/websocket/__init__.py
pionex_py/websocket/PrivateStream.py
pionex_py/websocket/PublicStream.py
pionex_py-1.0.3.dist-info/entry_points.txt
pionex_py-1.0.3.dist-info/LICENSE
pionex_py-1.0.3.dist-info/METADATA
pionex_py-1.0.3.dist-info/WHEEL
pionex_py-1.0.3.dist-info/RECORD
