Metadata-Version: 2.3
Name: pionex_py
Version: 1.0.3
Summary: Connector library for Pionex REST and WS API with enhanced error handling and performance.
License: MIT
Keywords: pionex,crypto,api,trading,websocket,rest
Author: Alejandro Rodríguez Moreno
Author-email: alejandrorodm@proton.me
Requires-Python: >=3.11,<4.0
Classifier: License :: OSI Approved :: MIT License
Classifier: Programming Language :: Python :: 3
Classifier: Programming Language :: Python :: 3.11
Classifier: Programming Language :: Python :: 3.12
Classifier: Programming Language :: Python :: 3.13
Requires-Dist: requests (>=2.31.0,<3.0.0)
Requires-Dist: retrying (>=1.3.4,<2.0.0)
Requires-Dist: websocket-client (>=1.7.0,<2.0.0)
Project-URL: Repository, https://github.com/alejandrorodm/pionex_py
